django_lazy_image/__init__.py
django_lazy_image/urls.py
django_lazy_image/views.py
django_lazy_image/conf/__init__.py
django_lazy_image/conf/defaults.py
django_lazy_image/templates/django_lazy_image/lazy-image.html
django_lazy_image/templatetags/__init__.py
django_lazy_image/templatetags/lazy_image.py
django_lazy_image-0.5.2.dist-info/METADATA
django_lazy_image-0.5.2.dist-info/RECORD
django_lazy_image-0.5.2.dist-info/WHEEL
django_lazy_image-0.5.2.dist-info/top_level.txt
