Metadata-Version: 2.1
Name: django-lazy-image
Version: 0.5.2
Summary: An image utility that renders images lazily as well as intrinsically sizes them.
Home-page: https://github.com/dan-gamble/django-lazy-image/
Author: Dan Gamble
Author-email: dan@dangamble.co.uk
License: UNKNOWN
Platform: UNKNOWN
Classifier: Development Status :: 5 - Production/Stable
Classifier: Framework :: Django :: 1.11
Classifier: Intended Audience :: Developers
Classifier: Natural Language :: English
Classifier: Programming Language :: Python :: 3
Classifier: Programming Language :: Python :: 3.6
Classifier: Programming Language :: Python :: 3 :: Only
Requires-Python: >=3
Provides-Extra: testing
Requires-Dist: sorl-thumbnail
Requires-Dist: Jinja2
Requires-Dist: django (<1.12,>=1.11)
Requires-Dist: django-jinja (>=2.2)
Provides-Extra: testing
Requires-Dist: coveralls; extra == 'testing'
Requires-Dist: pytest; extra == 'testing'
Requires-Dist: pytest-cov; extra == 'testing'
Requires-Dist: pytest-django; extra == 'testing'
Requires-Dist: pylint; extra == 'testing'
Requires-Dist: pylint-django; extra == 'testing'
Requires-Dist: pylint-mccabe; extra == 'testing'
Requires-Dist: isort; extra == 'testing'
